algorithms/__init__.py
algorithms/number.py
algorithms/search.py
algorithms/sorting.py
algorithms/data_structures/__init__.py
algorithms/data_structures/sequence.py
algorithms/data_structures/tree.py
cs_algorithms-0.0.9.dist-info/LICENSE
cs_algorithms-0.0.9.dist-info/METADATA
cs_algorithms-0.0.9.dist-info/WHEEL
cs_algorithms-0.0.9.dist-info/top_level.txt
cs_algorithms-0.0.9.dist-info/RECORD
