Metadata-Version: 2.1
Name: cs-algorithms
Version: 0.0.9
Summary: Sorting Algorithms & Data Structures
Home-page: https://github.com/michael-gvdw/cs-algorithms.git
Author: Michael Groenewegen van der Weijden
Author-email: 
License: UNKNOWN
Project-URL: GitHub, https://github.com/michael-gvdw/cs-algorithms.git
Project-URL: Linkedin, https://www.linkedin.com/in/michael-groenewegen-van-der-weijden-4234b9206/
Platform: UNKNOWN
Classifier: Programming Language :: Python :: 3
Classifier: License :: OSI Approved :: MIT License
Classifier: Operating System :: OS Independent
Requires-Python: >=3.8
